operetta/__init__.py
operetta/operetta_annotation.py
Operetta_tool-1.0.1.dist-info/LICENSE
Operetta_tool-1.0.1.dist-info/METADATA
Operetta_tool-1.0.1.dist-info/WHEEL
Operetta_tool-1.0.1.dist-info/top_level.txt
Operetta_tool-1.0.1.dist-info/RECORD
