Metadata-Version: 2.1
Name: Operetta-tool
Version: 1.0.1
Summary: operetta_tool
Author: Jakub Kubis
Author-email: jbiosystem@gmail.com
License: MIT
Keywords: python,opera,images,annotation,AI
Classifier: Development Status :: 3 - Alpha
Classifier: Programming Language :: Python :: 3
Classifier: Operating System :: MacOS :: MacOS X
Classifier: Operating System :: Microsoft :: Windows
Classifier: Operating System :: POSIX :: Linux
Requires-Python: >=3.6
License-File: LICENSE
Requires-Dist: regex
Requires-Dist: pandas
Requires-Dist: numpy
Requires-Dist: more-itertools
Requires-Dist: opencv-python
Requires-Dist: matplotlib
Requires-Dist: Pillow
Requires-Dist: h5py
Requires-Dist: tqdm
Requires-Dist: tifffile
Requires-Dist: joblib
